__init__.py
spc_plotly/__init__.py
spc_plotly/xmr.py
spc_plotly/helpers/__init__.py
spc_plotly/helpers/annotations.py
spc_plotly/helpers/axes_formats.py
spc_plotly/helpers/base_traces.py
spc_plotly/helpers/limit_lines.py
spc_plotly/helpers/menus.py
spc_plotly/helpers/signals.py
spc_plotly/utils/__init__.py
spc_plotly/utils/calc_xmr_func.py
spc_plotly/utils/combine_paths.py
spc_plotly/utils/endpoints.py
spc_plotly/utils/rounded_value.py
spc_plotly/utils/rounding_multiple.py
tests/__init__.py
tests/test_xmr.py
spc_plotly-0.1.3.dist-info/METADATA
spc_plotly-0.1.3.dist-info/WHEEL
spc_plotly-0.1.3.dist-info/top_level.txt
spc_plotly-0.1.3.dist-info/RECORD
