Metadata-Version: 2.1
Name: spc-plotly
Version: 0.1.3
Summary: XmR charts with Plotly
Author-email: Jeremy Colón <jeremycolon24@gmail.com>
Project-URL: Homepage, https://github.com/JeremyColon/spc_plotly
Classifier: Intended Audience :: Developers
Classifier: License :: OSI Approved :: MIT License
Classifier: Programming Language :: Python
Classifier: Programming Language :: Python :: 3
Classifier: Programming Language :: Python :: 3.6
Classifier: Programming Language :: Python :: 3.7
Classifier: Programming Language :: Python :: 3.8
Classifier: Programming Language :: Python :: 3.9
Classifier: Operating System :: OS Independent
Requires-Python: >=3.10.5
Requires-Dist: pandas >=2.2.1
Requires-Dist: numpy >=1.26.4
Requires-Dist: plotly >=5.20.0
